{
  "pages": [
    {
      "pageName": "Main",
      "children": [
        {
          "type": "DemoAppBar",
          "props": {
            "title": "Gihub Wacky Fun Go Party",
            "style": {
              "display": "none"
            }
          },
          "children": []
        },
        {
          "variantName": "3 Col with autosize",
          "type": "Row",
          "props": {},
          "children": [
            {
              "type": "Col",
              "props": {
                "auto": true
              },
              "children": [
                {
                  "type": "Box",
                  "props": {},
                  "children": [
                    {
                      "variantName": "Unsaved variant",
                      "type": "GithubRepoForm",
                      "props": {}
                    }
                  ],
                  "text": null
                }
              ],
              "text": null
            }
          ],
          "text": null
        },
        {
          "variantName": "3 Col with autosize",
          "type": "Row",
          "props": {},
          "children": [
            {
              "variantName": "Unsaved variant",
              "type": "GithubRepoContainer",
              "props": {}
            }
          ],
          "text": null
        }
      ],
      "props": {},
      "pageMetaInfo": [],
      "bodyScript": "",
      "pagePath": "/",
      "pageTitle": "PageSet1",
      "pageProps": [],
      "pageScript": ""
    }
  ]
}
